LICENSE.txt
MANIFEST.in
README.rst
dev_requirements.txt
requirements.txt
setup.py
distami/__init__.py
distami/cli.py
distami/core.py
distami/exceptions.py
distami/utils.py
distami.egg-info/PKG-INFO
distami.egg-info/SOURCES.txt
distami.egg-info/dependency_links.txt
distami.egg-info/entry_points.txt
distami.egg-info/not-zip-safe
distami.egg-info/requires.txt
distami.egg-info/top_level.txt