Metadata-Version: 1.1
Name: distami
Version: 1.0.5
Summary: Distribute Amazon Machine Images (AMIs) to the public
Home-page: https://github.com/Answers4AWS/distami
Author: Peter Sankauskas
Author-email: info@answersforaws.com
License: Copyright 2013 Answers for AWS LLC
